[
  {
    "true_class": "left_forehand",
    "frame": 5210,
    "predicted_class": "left_backhand",
    "probabilities": {
      "left_backhand": 0.443999892140653,
      "left_forehand": 0.27140371313702344,
      "left_serve": 0.12510070827365347,
      "right_backhand": 0.08735207179984743,
      "right_forehand": 0.031820689070140795,
      "right_serve": 0.04032292557868209
    }
  },
  {
    "true_class": "left_forehand",
    "frame": 5356,
    "predicted_class": "left_forehand",
    "probabilities": {
      "left_backhand": 0.021784725552795443,
      "left_forehand": 0.8394820689869069,
      "left_serve": 0.07277754996851321,
      "right_backhand": 0.02567140664193638,
      "right_forehand": 0.024761491082217695,
      "right_serve": 0.015522757767630423
    }
  },
  {
    "true_class": "right_forehand",
    "frame": 5396,
    "predicted_class": "right_forehand",
    "probabilities": {
      "left_backhand": 0.2019236145623375,
      "left_forehand": 0.05535588732417143,
      "left_serve": 0.1667169557528389,
      "right_backhand": 0.04324044987184164,
      "right_forehand": 0.46004410613612,
      "right_serve": 0.07271898635269065
    }
  },
  {
    "true_class": "left_serve",
    "frame": 6624,
    "predicted_class": "left_serve",
    "probabilities": {
      "left_backhand": 0.007311445897501914,
      "left_forehand": 0.24868348398707024,
      "left_serve": 0.5345895737743641,
      "right_backhand": 0.16922970767947926,
      "right_forehand": 0.026770864228686977,
      "right_serve": 0.01341492443289746
    }
  },
  {
    "true_class": "right_backhand",
    "frame": 6716,
    "predicted_class": "right_backhand",
    "probabilities": {
      "left_backhand": 0.014701257680323748,
      "left_forehand": 0.12855445227919415,
      "left_serve": 0.01526247780604692,
      "right_backhand": 0.6583424081252318,
      "right_forehand": 0.14511837058944557,
      "right_serve": 0.03802103351975779
    }
  },
  {
    "true_class": "left_forehand",
    "frame": 6771,
    "predicted_class": "left_forehand",
    "probabilities": {
      "left_backhand": 0.13986622630622192,
      "left_forehand": 0.6914328401731891,
      "left_serve": 0.050446241401009076,
      "right_backhand": 0.0563731435281657,
      "right_forehand": 0.026559284517325834,
      "right_serve": 0.035322264074088325
    }
  },
  {
    "true_class": "right_forehand",
    "frame": 6849,
    "predicted_class": "right_forehand",
    "probabilities": {
      "left_backhand": 0.003322069522072073,
      "left_forehand": 0.018388830440850053,
      "left_serve": 0.005845390326895692,
      "right_backhand": 0.00862175555766333,
      "right_forehand": 0.9360851395909622,
      "right_serve": 0.027736814561556567
    }
  },
  {
    "true_class": "left_forehand",
    "frame": 6950,
    "predicted_class": "left_forehand",
    "probabilities": {
      "left_backhand": 0.0017136856182706065,
      "left_forehand": 0.8218236994463581,
      "left_serve": 0.015674647745070283,
      "right_backhand": 0.08113098956940962,
      "right_forehand": 0.06124969819911935,
      "right_serve": 0.018407279421771925
    }
  },
  {
    "true_class": "left_serve",
    "frame": 8122,
    "predicted_class": "right_backhand",
    "probabilities": {
      "left_backhand": 0.21902433075549893,
      "left_forehand": 0.07893313450416911,
      "left_serve": 0.053159061906548906,
      "right_backhand": 0.3315646191867155,
      "right_forehand": 0.2888055118053061,
      "right_serve": 0.02851334184176129
    }
  },
  {
    "true_class": "right_backhand",
    "frame": 8210,
    "predicted_class": "right_backhand",
    "probabilities": {
      "left_backhand": 0.02379976064436023,
      "left_forehand": 0.09288806386885495,
      "left_serve": 0.022541044978581184,
      "right_backhand": 0.6091674030724039,
      "right_forehand": 0.19837471779951676,
      "right_serve": 0.05322900963628301
    }
  },
  {
    "true_class": "left_backhand",
    "frame": 8268,
    "predicted_class": "left_backhand",
    "probabilities": {
      "left_backhand": 0.5789992356222026,
      "left_forehand": 0.1671140386278334,
      "left_serve": 0.020524463119305298,
      "right_backhand": 0.07230543763029046,
      "right_forehand": 0.14626249736339358,
      "right_serve": 0.01479432763697459
    }
  },
  {
    "true_class": "right_forehand",
    "frame": 8364,
    "predicted_class": "right_forehand",
    "probabilities": {
      "left_backhand": 0.022508922676561512,
      "left_forehand": 0.08986099155193383,
      "left_serve": 0.009380650442864331,
      "right_backhand": 0.013768448456103413,
      "right_forehand": 0.7902766320939616,
      "right_serve": 0.07420435477857519
    }
  },
  {
    "true_class": "left_backhand",
    "frame": 9705,
    "predicted_class": "left_backhand",
    "probabilities": {
      "left_backhand": 0.7794354100442639,
      "left_forehand": 0.021351234417663064,
      "left_serve": 0.04513120975166938,
      "right_backhand": 0.015649151606812402,
      "right_forehand": 0.03428013856504418,
      "right_serve": 0.10415285561454728
    }
  },
  {
    "true_class": "right_forehand",
    "frame": 9787,
    "predicted_class": "right_forehand",
    "probabilities": {
      "left_backhand": 0.07024626635029764,
      "left_forehand": 0.09252574716583375,
      "left_serve": 0.05059629087438423,
      "right_backhand": 0.02265889385268442,
      "right_forehand": 0.6968695117111804,
      "right_serve": 0.06710329004561964
    }
  },
  {
    "true_class": "left_forehand",
    "frame": 9871,
    "predicted_class": "left_forehand",
    "probabilities": {
      "left_backhand": 0.053059726114425027,
      "left_forehand": 0.6886981597790045,
      "left_serve": 0.09229094876612434,
      "right_backhand": 0.07064104972320003,
      "right_forehand": 0.057537669274680736,
      "right_serve": 0.03777244634256535
    }
  },
  {
    "true_class": "right_serve",
    "frame": 10885,
    "predicted_class": "right_serve",
    "probabilities": {
      "left_backhand": 0.11461708947067119,
      "left_forehand": 0.13993800814170593,
      "left_serve": 0.013883652669261915,
      "right_backhand": 0.13824364600898512,
      "right_forehand": 0.26966739231289755,
      "right_serve": 0.3236502113964783
    }
  },
  {
    "true_class": "left_backhand",
    "frame": 10973,
    "predicted_class": "left_backhand",
    "probabilities": {
      "left_backhand": 0.6639556186926934,
      "left_forehand": 0.09044637320162159,
      "left_serve": 0.05073416027585286,
      "right_backhand": 0.07115874925058886,
      "right_forehand": 0.07496415172794495,
      "right_serve": 0.048740946851298275
    }
  },
  {
    "true_class": "right_forehand",
    "frame": 11093,
    "predicted_class": "right_forehand",
    "probabilities": {
      "left_backhand": 2.824707977138862e-18,
      "left_forehand": 1.9967804874616897e-05,
      "left_serve": 4.156901408659824e-05,
      "right_backhand": 0.0002374010714322787,
      "right_forehand": 0.999693239462165,
      "right_serve": 7.822647441328354e-06
    }
  },
  {
    "true_class": "left_serve",
    "frame": 13419,
    "predicted_class": "right_backhand",
    "probabilities": {
      "left_backhand": 7.544335701345568e-06,
      "left_forehand": 0.00837270812422061,
      "left_serve": 0.03854058451129353,
      "right_backhand": 0.932947938528536,
      "right_forehand": 0.002573182024499179,
      "right_serve": 0.017558042475749457
    }
  },
  {
    "true_class": "right_backhand",
    "frame": 13491,
    "predicted_class": "right_backhand",
    "probabilities": {
      "left_backhand": 0.016676643200577258,
      "left_forehand": 0.06410362973170691,
      "left_serve": 0.07138419736286228,
      "right_backhand": 0.5528421285078493,
      "right_forehand": 0.24469824654117345,
      "right_serve": 0.0502951546558308
    }
  },
  {
    "true_class": "left_serve",
    "frame": 14021,
    "predicted_class": "left_serve",
    "probabilities": {
      "left_backhand": 0.05619426587051326,
      "left_forehand": 0.1191519927497666,
      "left_serve": 0.39397801239671887,
      "right_backhand": 0.3567573283476766,
      "right_forehand": 0.044890129612341546,
      "right_serve": 0.029028271022983013
    }
  },
  {
    "true_class": "right_forehand",
    "frame": 14121,
    "predicted_class": "right_forehand",
    "probabilities": {
      "left_backhand": 0.00915156009261824,
      "left_forehand": 0.03377216190079434,
      "left_serve": 0.024683988837160303,
      "right_backhand": 0.29690663782854665,
      "right_forehand": 0.6197846737642484,
      "right_serve": 0.0157009775766321
    }
  },
  {
    "true_class": "left_forehand",
    "frame": 14203,
    "predicted_class": "left_forehand",
    "probabilities": {
      "left_backhand": 0.012324672945022756,
      "left_forehand": 0.7646251616556508,
      "left_serve": 0.026434322485987795,
      "right_backhand": 0.09729904907627576,
      "right_forehand": 0.08045585107612296,
      "right_serve": 0.018860942760939994
    }
  },
  {
    "true_class": "right_forehand",
    "frame": 14236,
    "predicted_class": "right_forehand",
    "probabilities": {
      "left_backhand": 0.13791001975494283,
      "left_forehand": 0.2125918439562936,
      "left_serve": 0.1523596960518406,
      "right_backhand": 0.09610349074888994,
      "right_forehand": 0.30605980102023056,
      "right_serve": 0.09497514846780242
    }
  },
  {
    "true_class": "left_forehand",
    "frame": 14339,
    "predicted_class": "left_forehand",
    "probabilities": {
      "left_backhand": 0.01473388910258758,
      "left_forehand": 0.7744408478506523,
      "left_serve": 0.02364103989459047,
      "right_backhand": 0.09231010725403696,
      "right_forehand": 0.06976005246042306,
      "right_serve": 0.025114063437709486
    }
  },
  {
    "true_class": "right_forehand",
    "frame": 14377,
    "predicted_class": "right_forehand",
    "probabilities": {
      "left_backhand": 0.16655392191669108,
      "left_forehand": 0.1146166642640262,
      "left_serve": 0.09121820031973991,
      "right_backhand": 0.10287977606308255,
      "right_forehand": 0.41563277215583017,
      "right_serve": 0.10909866528063006
    }
  },
  {
    "true_class": "left_forehand",
    "frame": 15333,
    "predicted_class": "left_forehand",
    "probabilities": {
      "left_backhand": 0.17244650847111903,
      "left_forehand": 0.6153209030484597,
      "left_serve": 0.10748281285893463,
      "right_backhand": 0.022046747619964592,
      "right_forehand": 0.021942216923434652,
      "right_serve": 0.06076081107808762
    }
  },
  {
    "true_class": "left_backhand",
    "frame": 15531,
    "predicted_class": "left_backhand",
    "probabilities": {
      "left_backhand": 0.5518916399063064,
      "left_forehand": 0.3448554307390272,
      "left_serve": 0.07981951013099688,
      "right_backhand": 0.0032039820237411733,
      "right_forehand": 0.005400214063256654,
      "right_serve": 0.01482922313667171
    }
  },
  {
    "true_class": "left_forehand",
    "frame": 16385,
    "predicted_class": "left_forehand",
    "probabilities": {
      "left_backhand": 0.3235070930768304,
      "left_forehand": 0.46116450412595145,
      "left_serve": 0.08965146415611988,
      "right_backhand": 0.04908609321296813,
      "right_forehand": 0.03374653990248263,
      "right_serve": 0.04284430552564748
    }
  },
  {
    "true_class": "right_forehand",
    "frame": 16474,
    "predicted_class": "right_forehand",
    "probabilities": {
      "left_backhand": 0.015306935815000908,
      "left_forehand": 0.06336173374942114,
      "left_serve": 0.00793270924777195,
      "right_backhand": 0.011351423847508268,
      "right_forehand": 0.8298757707073809,
      "right_serve": 0.07217142663291684
    }
  },
  {
    "true_class": "left_forehand",
    "frame": 16527,
    "predicted_class": "left_forehand",
    "probabilities": {
      "left_backhand": 0.011559718050697164,
      "left_forehand": 0.9372532720566085,
      "left_serve": 0.020772678606395978,
      "right_backhand": 0.015309134268740024,
      "right_forehand": 0.01267792614959545,
      "right_serve": 0.002427270867962912
    }
  },
  {
    "true_class": "left_serve",
    "frame": 17716,
    "predicted_class": "left_serve",
    "probabilities": {
      "left_backhand": 0.0139456222731547,
      "left_forehand": 0.17078120406191855,
      "left_serve": 0.5533886445017466,
      "right_backhand": 0.22628007412188555,
      "right_forehand": 0.022535839710232916,
      "right_serve": 0.01306861533106179
    }
  },
  {
    "true_class": "right_backhand",
    "frame": 17798,
    "predicted_class": "right_backhand",
    "probabilities": {
      "left_backhand": 0.015109167684665978,
      "left_forehand": 0.10667354274847235,
      "left_serve": 0.026240517872339535,
      "right_backhand": 0.6864010281967836,
      "right_forehand": 0.1141189814114006,
      "right_serve": 0.05145676208633806
    }
  },
  {
    "true_class": "left_serve",
    "frame": 18775,
    "predicted_class": "right_backhand",
    "probabilities": {
      "left_backhand": 0.19573386580781993,
      "left_forehand": 0.05639025079727416,
      "left_serve": 0.05829770397508203,
      "right_backhand": 0.3418940988051601,
      "right_forehand": 0.31352438141909444,
      "right_serve": 0.034159699195569375
    }
  },
  {
    "true_class": "right_backhand",
    "frame": 18863,
    "predicted_class": "right_backhand",
    "probabilities": {
      "left_backhand": 0.013140011903580627,
      "left_forehand": 0.09068102697251482,
      "left_serve": 0.022486404407070646,
      "right_backhand": 0.635960653772478,
      "right_forehand": 0.18099413697909478,
      "right_serve": 0.05673776596526113
    }
  },
  {
    "true_class": "left_forehand",
    "frame": 18952,
    "predicted_class": "left_forehand",
    "probabilities": {
      "left_backhand": 0.03816279116255098,
      "left_forehand": 0.6854733793395276,
      "left_serve": 0.06098260733843711,
      "right_backhand": 0.07876369232909006,
      "right_forehand": 0.1051841536355814,
      "right_serve": 0.0314333761948129
    }
  },
  {
    "true_class": "left_backhand",
    "frame": 21109,
    "predicted_class": "left_backhand",
    "probabilities": {
      "left_backhand": 0.8205192070486109,
      "left_forehand": 0.028248665585887744,
      "left_serve": 0.036017584511151744,
      "right_backhand": 0.019257894194769875,
      "right_forehand": 0.02953068136062214,
      "right_serve": 0.0664259672989575
    }
  },
  {
    "true_class": "left_backhand",
    "frame": 21698,
    "predicted_class": "left_backhand",
    "probabilities": {
      "left_backhand": 0.7690093995160566,
      "left_forehand": 0.059857832050493644,
      "left_serve": 0.05866654464706012,
      "right_backhand": 0.01605933549844613,
      "right_forehand": 0.026445178127349134,
      "right_serve": 0.06996171016059426
    }
  },
  {
    "true_class": "right_forehand",
    "frame": 21817,
    "predicted_class": "right_forehand",
    "probabilities": {
      "left_backhand": 0.22412878003781297,
      "left_forehand": 0.13715710736601308,
      "left_serve": 0.24659780184069827,
      "right_backhand": 0.0027556631051365455,
      "right_forehand": 0.312754544971838,
      "right_serve": 0.07660610267850114
    }
  },
  {
    "true_class": "right_forehand",
    "frame": 21980,
    "predicted_class": "left_backhand",
    "probabilities": {
      "left_backhand": 0.7867738797386544,
      "left_forehand": 0.0008400872590059969,
      "left_serve": 0.1805559374775995,
      "right_backhand": 0.028639015326052057,
      "right_forehand": 0.00023075620815115496,
      "right_serve": 0.002960323990536889
    }
  },
  {
    "true_class": "left_backhand",
    "frame": 23909,
    "predicted_class": "right_forehand",
    "probabilities": {
      "left_backhand": 0.1447334731535149,
      "left_forehand": 0.21943266013738283,
      "left_serve": 0.0720319500741814,
      "right_backhand": 0.08759462762079305,
      "right_forehand": 0.2983629584892975,
      "right_serve": 0.1778443305248303
    }
  },
  {
    "true_class": "right_forehand",
    "frame": 24014,
    "predicted_class": "left_forehand",
    "probabilities": {
      "left_backhand": 0.016398082834927028,
      "left_forehand": 0.5472286013518656,
      "left_serve": 0.018980145277197154,
      "right_backhand": 0.1930336279039384,
      "right_forehand": 0.21924012403864898,
      "right_serve": 0.005119418593422894
    }
  },
  {
    "true_class": "left_forehand",
    "frame": 24101,
    "predicted_class": "left_forehand",
    "probabilities": {
      "left_backhand": 0.014004215815957646,
      "left_forehand": 0.8303669294263434,
      "left_serve": 0.06454550163469203,
      "right_backhand": 0.0439014588863276,
      "right_forehand": 0.011015528801833773,
      "right_serve": 0.036166365434845436
    }
  },
  {
    "true_class": "right_backhand",
    "frame": 24181,
    "predicted_class": "right_backhand",
    "probabilities": {
      "left_backhand": 0.0013288787193982466,
      "left_forehand": 0.0886946505005064,
      "left_serve": 0.027055866663779987,
      "right_backhand": 0.8690100049487054,
      "right_forehand": 0.005272440932607296,
      "right_serve": 0.008638158235002705
    }
  },
  {
    "true_class": "left_backhand",
    "frame": 24222,
    "predicted_class": "right_forehand",
    "probabilities": {
      "left_backhand": 5.728235247981916e-05,
      "left_forehand": 0.0024777223580215208,
      "left_serve": 0.0009184041539466586,
      "right_backhand": 0.012068520517054421,
      "right_forehand": 0.9585693926290707,
      "right_serve": 0.025908677989426684
    }
  },
  {
    "true_class": "right_forehand",
    "frame": 24333,
    "predicted_class": "left_backhand",
    "probabilities": {
      "left_backhand": 0.9997197045658929,
      "left_forehand": 1.2263943167093634e-05,
      "left_serve": 0.00019539616516927672,
      "right_backhand": 1.82275459291568e-06,
      "right_forehand": 1.3702348432170056e-05,
      "right_serve": 5.711022274533745e-05
    }
  },
  {
    "true_class": "right_forehand",
    "frame": 24435,
    "predicted_class": "left_serve",
    "probabilities": {
      "left_backhand": 6.8934772805995645e-06,
      "left_forehand": 0.0009254766004067783,
      "left_serve": 0.8061394462435322,
      "right_backhand": 0.003895272975398269,
      "right_forehand": 0.18883235868039885,
      "right_serve": 0.0002005520229832729
    }
  },
  {
    "true_class": "left_serve",
    "frame": 25804,
    "predicted_class": "right_backhand",
    "probabilities": {
      "left_backhand": 5.1600551817510555e-06,
      "left_forehand": 0.02847757918729053,
      "left_serve": 0.0863992304405729,
      "right_backhand": 0.7209157527540925,
      "right_forehand": 0.14523048809965067,
      "right_serve": 0.018971789463211774
    }
  },
  {
    "true_class": "right_backhand",
    "frame": 25875,
    "predicted_class": "right_backhand",
    "probabilities": {
      "left_backhand": 0.019719155738629278,
      "left_forehand": 0.04966110937264139,
      "left_serve": 0.05219705443795136,
      "right_backhand": 0.6352822983677499,
      "right_forehand": 0.18787601197532636,
      "right_serve": 0.055264370107701834
    }
  },
  {
    "true_class": "left_backhand",
    "frame": 25947,
    "predicted_class": "left_backhand",
    "probabilities": {
      "left_backhand": 0.741431516430386,
      "left_forehand": 0.08771584768374659,
      "left_serve": 0.040180346618262835,
      "right_backhand": 0.05957955797444312,
      "right_forehand": 0.03388547172076465,
      "right_serve": 0.03720725957239688
    }
  },
  {
    "true_class": "right_forehand",
    "frame": 26065,
    "predicted_class": "right_forehand",
    "probabilities": {
      "left_backhand": 0.027350617643563533,
      "left_forehand": 0.3310199452678166,
      "left_serve": 0.006767053065652504,
      "right_backhand": 0.00272056410661735,
      "right_forehand": 0.5996096168023004,
      "right_serve": 0.032532203114049564
    }
  },
  {
    "true_class": "left_serve",
    "frame": 27250,
    "predicted_class": "left_forehand",
    "probabilities": {
      "left_backhand": 0.00581064909718079,
      "left_forehand": 0.40123071161486185,
      "left_serve": 0.3270189018268268,
      "right_backhand": 0.23430789780160913,
      "right_forehand": 0.01777712508276178,
      "right_serve": 0.013854714576759472
    }
  },
  {
    "true_class": "right_backhand",
    "frame": 27329,
    "predicted_class": "right_backhand",
    "probabilities": {
      "left_backhand": 0.038999641895995966,
      "left_forehand": 0.04244816356537019,
      "left_serve": 0.047647109542323186,
      "right_backhand": 0.58573872915219,
      "right_forehand": 0.1987351267436905,
      "right_serve": 0.08643122910043018
    }
  },
  {
    "true_class": "left_backhand",
    "frame": 27379,
    "predicted_class": "left_backhand",
    "probabilities": {
      "left_backhand": 0.5742194209429867,
      "left_forehand": 0.15348631498470544,
      "left_serve": 0.02387619662532812,
      "right_backhand": 0.0947987415294471,
      "right_forehand": 0.1268344517441756,
      "right_serve": 0.02678487417335701
    }
  },
  {
    "true_class": "left_backhand",
    "frame": 28826,
    "predicted_class": "left_backhand",
    "probabilities": {
      "left_backhand": 0.7857315521330724,
      "left_forehand": 0.024499503518726425,
      "left_serve": 0.05657954214391196,
      "right_backhand": 0.04185738384780423,
      "right_forehand": 0.03588219603855377,
      "right_serve": 0.05544982231793139
    }
  },
  {
    "true_class": "right_forehand",
    "frame": 28927,
    "predicted_class": "right_forehand",
    "probabilities": {
      "left_backhand": 0.032954317321673386,
      "left_forehand": 0.08693158133130095,
      "left_serve": 0.02149998330391629,
      "right_backhand": 0.018133183282386195,
      "right_forehand": 0.7554700306202354,
      "right_serve": 0.08501090414048774
    }
  },
  {
    "true_class": "left_backhand",
    "frame": 30425,
    "predicted_class": "right_serve",
    "probabilities": {
      "left_backhand": 0.09377859708332816,
      "left_forehand": 0.13703624747581267,
      "left_serve": 0.19107042601712837,
      "right_backhand": 0.09177995235861522,
      "right_forehand": 0.08300852177914403,
      "right_serve": 0.4033262552859715
    }
  },
  {
    "true_class": "right_forehand",
    "frame": 30508,
    "predicted_class": "right_forehand",
    "probabilities": {
      "left_backhand": 2.601121672914894e-05,
      "left_forehand": 0.0005290671192953192,
      "left_serve": 0.00011632016816654163,
      "right_backhand": 0.0033914196749951155,
      "right_forehand": 0.9915274100183692,
      "right_serve": 0.004409771802444701
    }
  },
  {
    "true_class": "left_forehand",
    "frame": 30597,
    "predicted_class": "right_forehand",
    "probabilities": {
      "left_backhand": 1.2449669104325285e-10,
      "left_forehand": 0.1121224650479052,
      "left_serve": 0.0003763370489390778,
      "right_backhand": 0.01857920407508092,
      "right_forehand": 0.8688180099571374,
      "right_serve": 0.0001039837464407047
    }
  },
  {
    "true_class": "right_forehand",
    "frame": 30688,
    "predicted_class": "left_backhand",
    "probabilities": {
      "left_backhand": 0.9501213359816927,
      "left_forehand": 0.0014439967853768457,
      "left_serve": 0.011711477100138572,
      "right_backhand": 0.01631018042559138,
      "right_forehand": 0.01778021630715815,
      "right_serve": 0.0026327934000425005
    }
  },
  {
    "true_class": "left_serve",
    "frame": 32535,
    "predicted_class": "left_serve",
    "probabilities": {
      "left_backhand": 0.059542097029139505,
      "left_forehand": 0.1461091610059673,
      "left_serve": 0.4415409690963876,
      "right_backhand": 0.27213278578543565,
      "right_forehand": 0.04991480091195554,
      "right_serve": 0.03076018617111429
    }
  },
  {
    "true_class": "right_forehand",
    "frame": 32631,
    "predicted_class": "right_forehand",
    "probabilities": {
      "left_backhand": 0.01265604852241576,
      "left_forehand": 0.046253016645610136,
      "left_serve": 0.025303282724069072,
      "right_backhand": 0.12272791978201215,
      "right_forehand": 0.7465862607039297,
      "right_serve": 0.04647347162196319
    }
  },
  {
    "true_class": "left_forehand",
    "frame": 32708,
    "predicted_class": "left_forehand",
    "probabilities": {
      "left_backhand": 0.048294467948566115,
      "left_forehand": 0.6760290886318555,
      "left_serve": 0.06339990917665317,
      "right_backhand": 0.08494598158546353,
      "right_forehand": 0.09865292011895901,
      "right_serve": 0.028677632538502657
    }
  },
  {
    "true_class": "left_forehand",
    "frame": 32831,
    "predicted_class": "left_forehand",
    "probabilities": {
      "left_backhand": 0.018770422004082445,
      "left_forehand": 0.7262971511699099,
      "left_serve": 0.03439835583824148,
      "right_backhand": 0.017257236107090387,
      "right_forehand": 0.007681226686613165,
      "right_serve": 0.1955956081940626
    }
  },
  {
    "true_class": "left_serve",
    "frame": 33796,
    "predicted_class": "right_backhand",
    "probabilities": {
      "left_backhand": 0.17166742525909123,
      "left_forehand": 0.04878824379895069,
      "left_serve": 0.046770513702500655,
      "right_backhand": 0.37740243765345977,
      "right_forehand": 0.3298015414326451,
      "right_serve": 0.025569838153352446
    }
  },
  {
    "true_class": "right_backhand",
    "frame": 33892,
    "predicted_class": "right_backhand",
    "probabilities": {
      "left_backhand": 0.02481099673876754,
      "left_forehand": 0.0656697287470543,
      "left_serve": 0.013811839443079472,
      "right_backhand": 0.594960471319779,
      "right_forehand": 0.25603942900578497,
      "right_serve": 0.04470753474553464
    }
  },
  {
    "true_class": "left_backhand",
    "frame": 33959,
    "predicted_class": "left_backhand",
    "probabilities": {
      "left_backhand": 0.5991486874240243,
      "left_forehand": 0.12360572046491154,
      "left_serve": 0.026077149037169164,
      "right_backhand": 0.06240302461997129,
      "right_forehand": 0.1622137870869178,
      "right_serve": 0.02655163136700587
    }
  },
  {
    "true_class": "right_forehand",
    "frame": 34057,
    "predicted_class": "right_forehand",
    "probabilities": {
      "left_backhand": 0.018112981559116833,
      "left_forehand": 0.04182428088017151,
      "left_serve": 0.004729824663549386,
      "right_backhand": 0.022048412571735388,
      "right_forehand": 0.8982571874218814,
      "right_serve": 0.015027312903545493
    }
  },
  {
    "true_class": "right_serve",
    "frame": 38938,
    "predicted_class": "right_serve",
    "probabilities": {
      "left_backhand": 0.11612675683168434,
      "left_forehand": 0.145942261221362,
      "left_serve": 0.019950370518252315,
      "right_backhand": 0.28303951676916583,
      "right_forehand": 0.12024238447158385,
      "right_serve": 0.3146987101879517
    }
  },
  {
    "true_class": "left_backhand",
    "frame": 39023,
    "predicted_class": "left_backhand",
    "probabilities": {
      "left_backhand": 0.6782784596890536,
      "left_forehand": 0.16441144848570918,
      "left_serve": 0.023054839232958146,
      "right_backhand": 0.031707793223975815,
      "right_forehand": 0.05570534820860819,
      "right_serve": 0.04684211115969496
    }
  },
  {
    "true_class": "right_forehand",
    "frame": 39099,
    "predicted_class": "right_forehand",
    "probabilities": {
      "left_backhand": 0.08304923663080963,
      "left_forehand": 0.2010489833662683,
      "left_serve": 0.056044928767520104,
      "right_backhand": 0.06802765770898628,
      "right_forehand": 0.5683336295585996,
      "right_serve": 0.02349556396781603
    }
  },
  {
    "true_class": "right_serve",
    "frame": 39895,
    "predicted_class": "right_serve",
    "probabilities": {
      "left_backhand": 0.2470779859352119,
      "left_forehand": 0.10206843572293875,
      "left_serve": 0.013892959030718438,
      "right_backhand": 0.2825389315506227,
      "right_forehand": 0.06058532211783128,
      "right_serve": 0.293836365642677
    }
  },
  {
    "true_class": "left_forehand",
    "frame": 39990,
    "predicted_class": "left_forehand",
    "probabilities": {
      "left_backhand": 0.16163190109297224,
      "left_forehand": 0.7314952440912287,
      "left_serve": 0.018575917474662997,
      "right_backhand": 0.033717978356492886,
      "right_forehand": 0.031226170851734934,
      "right_serve": 0.02335278813290831
    }
  },
  {
    "true_class": "right_forehand",
    "frame": 40068,
    "predicted_class": "right_forehand",
    "probabilities": {
      "left_backhand": 0.05033301377307308,
      "left_forehand": 0.1754122724941967,
      "left_serve": 0.03382365344252781,
      "right_backhand": 0.31922548904335285,
      "right_forehand": 0.40649526419436666,
      "right_serve": 0.014710307052482881
    }
  },
  {
    "true_class": "left_forehand",
    "frame": 40162,
    "predicted_class": "left_forehand",
    "probabilities": {
      "left_backhand": 0.012662856118225908,
      "left_forehand": 0.9271715536255238,
      "left_serve": 0.035160434679295596,
      "right_backhand": 0.009450018761440871,
      "right_forehand": 0.008128605424649233,
      "right_serve": 0.007426531390864416
    }
  },
  {
    "true_class": "right_forehand",
    "frame": 40215,
    "predicted_class": "right_forehand",
    "probabilities": {
      "left_backhand": 0.07062005152915192,
      "left_forehand": 0.07707501990421949,
      "left_serve": 0.07314584681028975,
      "right_backhand": 0.06765439652339188,
      "right_forehand": 0.699289497802927,
      "right_serve": 0.012215187430019923
    }
  },
  {
    "true_class": "left_serve",
    "frame": 41519,
    "predicted_class": "right_forehand",
    "probabilities": {
      "left_backhand": 5.951140519665966e-17,
      "left_forehand": 0.0029958936342411448,
      "left_serve": 0.0003487206701753344,
      "right_backhand": 0.023714969694694797,
      "right_forehand": 0.9728779552744681,
      "right_serve": 6.246072642069512e-05
    }
  },
  {
    "true_class": "right_forehand",
    "frame": 41614,
    "predicted_class": "left_backhand",
    "probabilities": {
      "left_backhand": 0.32291664815604515,
      "left_forehand": 0.19969512129180514,
      "left_serve": 0.19924030043555738,
      "right_backhand": 0.25891426876422624,
      "right_forehand": 0.008821040446782042,
      "right_serve": 0.010412620905584067
    }
  },
  {
    "true_class": "left_forehand",
    "frame": 41698,
    "predicted_class": "left_forehand",
    "probabilities": {
      "left_backhand": 0.005213807654319953,
      "left_forehand": 0.9432628419059174,
      "left_serve": 0.027229515241212268,
      "right_backhand": 0.01153435936558533,
      "right_forehand": 0.009185139400917927,
      "right_serve": 0.0035743364320470162
    }
  },
  {
    "true_class": "right_backhand",
    "frame": 41757,
    "predicted_class": "right_backhand",
    "probabilities": {
      "left_backhand": 0.03643093152753193,
      "left_forehand": 0.20877175874227485,
      "left_serve": 0.05699901762457572,
      "right_backhand": 0.5690670056235978,
      "right_forehand": 0.10091540460200359,
      "right_serve": 0.027815881880016262
    }
  },
  {
    "true_class": "left_forehand",
    "frame": 41866,
    "predicted_class": "left_forehand",
    "probabilities": {
      "left_backhand": 0.0019400990451476385,
      "left_forehand": 0.9930551920871419,
      "left_serve": 4.2616564124302484e-07,
      "right_backhand": 0.0019039169561986093,
      "right_forehand": 0.003100365745870502,
      "right_serve": 9.323223922377694e-27
    }
  },
  {
    "true_class": "right_forehand",
    "frame": 41921,
    "predicted_class": "left_forehand",
    "probabilities": {
      "left_backhand": 0.005101140511481662,
      "left_forehand": 0.6141376274914455,
      "left_serve": 2.8953990499065803e-06,
      "right_backhand": 0.12380427410266792,
      "right_forehand": 0.25695406249535496,
      "right_serve": 2.1501359681375834e-23
    }
  },
  {
    "true_class": "left_serve",
    "frame": 43196,
    "predicted_class": "left_serve",
    "probabilities": {
      "left_backhand": 0.01624896511791351,
      "left_forehand": 0.3503602112350143,
      "left_serve": 0.6070046079321656,
      "right_backhand": 0.01527330228537502,
      "right_forehand": 0.003916113163250311,
      "right_serve": 0.007196800266281182
    }
  },
  {
    "true_class": "right_backhand",
    "frame": 43258,
    "predicted_class": "right_backhand",
    "probabilities": {
      "left_backhand": 0.02836871942699357,
      "left_forehand": 0.15546708361501427,
      "left_serve": 0.04201709180439536,
      "right_backhand": 0.7121949615778543,
      "right_forehand": 0.039794653957342864,
      "right_serve": 0.022157489618399653
    }
  },
  {
    "true_class": "left_forehand",
    "frame": 43358,
    "predicted_class": "left_forehand",
    "probabilities": {
      "left_backhand": 0.009516770348910701,
      "left_forehand": 0.9133885625524187,
      "left_serve": 0.04815563895301055,
      "right_backhand": 0.013022787675879985,
      "right_forehand": 0.009292655931832134,
      "right_serve": 0.006623584537947755
    }
  },
  {
    "true_class": "right_forehand",
    "frame": 43411,
    "predicted_class": "right_forehand",
    "probabilities": {
      "left_backhand": 0.03190286034684394,
      "left_forehand": 0.030690916255893083,
      "left_serve": 0.042287772327815235,
      "right_backhand": 0.09007230888210181,
      "right_forehand": 0.7467253764226567,
      "right_serve": 0.05832076576468936
    }
  },
  {
    "true_class": "left_forehand",
    "frame": 44927,
    "predicted_class": "left_forehand",
    "probabilities": {
      "left_backhand": 0.20975640788306876,
      "left_forehand": 0.6850255274019901,
      "left_serve": 0.027583355652985288,
      "right_backhand": 0.011711967434742144,
      "right_forehand": 0.020033994827111115,
      "right_serve": 0.045888746800102666
    }
  },
  {
    "true_class": "right_serve",
    "frame": 46132,
    "predicted_class": "right_serve",
    "probabilities": {
      "left_backhand": 0.03855520097003393,
      "left_forehand": 0.16678460210513169,
      "left_serve": 0.036975940349515096,
      "right_backhand": 0.07996389443550578,
      "right_forehand": 0.025450895307019668,
      "right_serve": 0.6522694668327939
    }
  },
  {
    "true_class": "left_backhand",
    "frame": 46221,
    "predicted_class": "right_forehand",
    "probabilities": {
      "left_backhand": 2.0668380105318697e-13,
      "left_forehand": 0.030083537212785758,
      "left_serve": 0.001083547183543902,
      "right_backhand": 0.06276534403040747,
      "right_forehand": 0.9048807756445926,
      "right_serve": 0.001186795928463682
    }
  },
  {
    "true_class": "right_backhand",
    "frame": 46287,
    "predicted_class": "left_forehand",
    "probabilities": {
      "left_backhand": 0.026604905809626853,
      "left_forehand": 0.4389399513587698,
      "left_serve": 0.0299447842858243,
      "right_backhand": 0.4095970934425333,
      "right_forehand": 0.07862941434515544,
      "right_serve": 0.016283850758090516
    }
  },
  {
    "true_class": "left_backhand",
    "frame": 46357,
    "predicted_class": "left_forehand",
    "probabilities": {
      "left_backhand": 0.07934871304150329,
      "left_forehand": 0.5104555261035959,
      "left_serve": 0.02077254982095776,
      "right_backhand": 0.03870933302841042,
      "right_forehand": 0.2556886558505845,
      "right_serve": 0.0950252221549482
    }
  },
  {
    "true_class": "left_serve",
    "frame": 48858,
    "predicted_class": "left_serve",
    "probabilities": {
      "left_backhand": 0.018648151357292714,
      "left_forehand": 0.4285472997926321,
      "left_serve": 0.5296976639169662,
      "right_backhand": 0.012561281630349513,
      "right_forehand": 0.0026704699176022637,
      "right_serve": 0.007875133385157263
    }
  },
  {
    "true_class": "right_forehand",
    "frame": 48964,
    "predicted_class": "right_forehand",
    "probabilities": {
      "left_backhand": 0.033877924142598596,
      "left_forehand": 0.14890488704129692,
      "left_serve": 0.029246157813413033,
      "right_backhand": 0.22831611947974126,
      "right_forehand": 0.546899727195692,
      "right_serve": 0.012755184327258131
    }
  },
  {
    "true_class": "left_forehand",
    "frame": 49064,
    "predicted_class": "left_forehand",
    "probabilities": {
      "left_backhand": 0.007671195146565773,
      "left_forehand": 0.9103864606781028,
      "left_serve": 0.04790738713183577,
      "right_backhand": 0.011661628416856102,
      "right_forehand": 0.015701712451956118,
      "right_serve": 0.006671616174683304
    }
  },
  {
    "true_class": "right_backhand",
    "frame": 49108,
    "predicted_class": "left_forehand",
    "probabilities": {
      "left_backhand": 0.1483223021693012,
      "left_forehand": 0.23172818356508357,
      "left_serve": 0.18463508321546748,
      "right_backhand": 0.21242486812075526,
      "right_forehand": 0.16275986999351205,
      "right_serve": 0.0601296929358805
    }
  },
  {
    "true_class": "left_serve",
    "frame": 50099,
    "predicted_class": "left_serve",
    "probabilities": {
      "left_backhand": 0.020446508967140974,
      "left_forehand": 0.3290784978735057,
      "left_serve": 0.6217540706490678,
      "right_backhand": 0.017037463073480814,
      "right_forehand": 0.003309087210622534,
      "right_serve": 0.008374372226182177
    }
  },
  {
    "true_class": "right_backhand",
    "frame": 50188,
    "predicted_class": "right_backhand",
    "probabilities": {
      "left_backhand": 0.014843327389930416,
      "left_forehand": 0.07308273203434741,
      "left_serve": 0.010967831091852637,
      "right_backhand": 0.8248844222988271,
      "right_forehand": 0.06658151035521821,
      "right_serve": 0.009640176829824303
    }
  },
  {
    "true_class": "left_forehand",
    "frame": 50280,
    "predicted_class": "left_forehand",
    "probabilities": {
      "left_backhand": 0.021661252751159238,
      "left_forehand": 0.8589659407703992,
      "left_serve": 0.06918778211508245,
      "right_backhand": 0.025186054611667674,
      "right_forehand": 0.021277264829400087,
      "right_serve": 0.0037217049222912544
    }
  },
  {
    "true_class": "right_backhand",
    "frame": 50334,
    "predicted_class": "right_backhand",
    "probabilities": {
      "left_backhand": 0.11570930896691754,
      "left_forehand": 0.19193379506387756,
      "left_serve": 0.10591820676493995,
      "right_backhand": 0.32541194467147766,
      "right_forehand": 0.22265329676322915,
      "right_serve": 0.038373447769558144
    }
  },
  {
    "true_class": "right_serve",
    "frame": 51203,
    "predicted_class": "right_backhand",
    "probabilities": {
      "left_backhand": 0.23382305906130527,
      "left_forehand": 0.10093130214503594,
      "left_serve": 0.017863359061449445,
      "right_backhand": 0.28293689920970866,
      "right_forehand": 0.09206834896534925,
      "right_serve": 0.27237703155715165
    }
  },
  {
    "true_class": "left_backhand",
    "frame": 51297,
    "predicted_class": "left_backhand",
    "probabilities": {
      "left_backhand": 0.6214133069339668,
      "left_forehand": 0.14181081200994516,
      "left_serve": 0.046025840997507055,
      "right_backhand": 0.035743937058876435,
      "right_forehand": 0.11428165682138389,
      "right_serve": 0.04072444617832064
    }
  },
  {
    "true_class": "right_backhand",
    "frame": 51347,
    "predicted_class": "right_backhand",
    "probabilities": {
      "left_backhand": 0.09073159547742339,
      "left_forehand": 0.22035371531887976,
      "left_serve": 0.05805908726899654,
      "right_backhand": 0.4114402989223127,
      "right_forehand": 0.1842775019964589,
      "right_serve": 0.035137801015928644
    }
  },
  {
    "true_class": "left_forehand",
    "frame": 51428,
    "predicted_class": "left_backhand",
    "probabilities": {
      "left_backhand": 0.6584195116374224,
      "left_forehand": 0.2578689268354076,
      "left_serve": 0.024711365872738048,
      "right_backhand": 0.03520580547926676,
      "right_forehand": 0.014732352600317694,
      "right_serve": 0.009062037574847697
    }
  },
  {
    "true_class": "right_forehand",
    "frame": 51524,
    "predicted_class": "right_forehand",
    "probabilities": {
      "left_backhand": 0.03437654953768951,
      "left_forehand": 0.08520525923413032,
      "left_serve": 0.030416935990151828,
      "right_backhand": 0.05715508940665255,
      "right_forehand": 0.566422894068904,
      "right_serve": 0.2264232717624719
    }
  },
  {
    "true_class": "right_backhand",
    "frame": 51634,
    "predicted_class": "right_backhand",
    "probabilities": {
      "left_backhand": 0.10805087744067333,
      "left_forehand": 0.1297268494655363,
      "left_serve": 0.1803192314201816,
      "right_backhand": 0.4702354284246442,
      "right_forehand": 0.088979913157779,
      "right_serve": 0.022687700091185717
    }
  },
  {
    "true_class": "left_backhand",
    "frame": 51741,
    "predicted_class": "left_backhand",
    "probabilities": {
      "left_backhand": 0.985443662311578,
      "left_forehand": 0.0026300627410974983,
      "left_serve": 0.0023254224901700705,
      "right_backhand": 0.004280763539438643,
      "right_forehand": 0.002876415488795759,
      "right_serve": 0.0024436734289198666
    }
  },
  {
    "true_class": "right_forehand",
    "frame": 51860,
    "predicted_class": "left_forehand",
    "probabilities": {
      "left_backhand": 0.022514801846933805,
      "left_forehand": 0.4982269062369967,
      "left_serve": 0.039486331559110514,
      "right_backhand": 0.006898355795591534,
      "right_forehand": 0.32341000253311303,
      "right_serve": 0.10946360202825427
    }
  },
  {
    "true_class": "left_backhand",
    "frame": 53074,
    "predicted_class": "left_backhand",
    "probabilities": {
      "left_backhand": 0.7031503459038427,
      "left_forehand": 0.1874583927810827,
      "left_serve": 0.02193189185266858,
      "right_backhand": 0.016409079435528013,
      "right_forehand": 0.016806219004790904,
      "right_serve": 0.05424407102208697
    }
  },
  {
    "true_class": "right_backhand",
    "frame": 53127,
    "predicted_class": "right_backhand",
    "probabilities": {
      "left_backhand": 0.07533941318520418,
      "left_forehand": 0.1909118458619847,
      "left_serve": 0.03004503743656826,
      "right_backhand": 0.5232061533140666,
      "right_forehand": 0.12974881003493818,
      "right_serve": 0.05074874016723797
    }
  },
  {
    "true_class": "left_serve",
    "frame": 54508,
    "predicted_class": "left_serve",
    "probabilities": {
      "left_backhand": 0.020113649025301966,
      "left_forehand": 0.28019437747977755,
      "left_serve": 0.6691885632571974,
      "right_backhand": 0.01864680904311918,
      "right_forehand": 0.0031970900544575276,
      "right_serve": 0.008659511140146263
    }
  },
  {
    "true_class": "right_backhand",
    "frame": 54591,
    "predicted_class": "right_backhand",
    "probabilities": {
      "left_backhand": 0.010025119298941818,
      "left_forehand": 0.09080530523690007,
      "left_serve": 0.013345985990422228,
      "right_backhand": 0.8390921728530498,
      "right_forehand": 0.02922946676659239,
      "right_serve": 0.01750194985409369
    }
  },
  {
    "true_class": "left_forehand",
    "frame": 54682,
    "predicted_class": "left_forehand",
    "probabilities": {
      "left_backhand": 0.015111556436575822,
      "left_forehand": 0.9089784435337359,
      "left_serve": 0.05277405021220503,
      "right_backhand": 0.012898853619942205,
      "right_forehand": 0.007527574993051001,
      "right_serve": 0.0027095212044900866
    }
  },
  {
    "true_class": "right_backhand",
    "frame": 54740,
    "predicted_class": "right_backhand",
    "probabilities": {
      "left_backhand": 0.09019966063375168,
      "left_forehand": 0.2103597793514264,
      "left_serve": 0.07093303016007638,
      "right_backhand": 0.47121203502097253,
      "right_forehand": 0.1249890056137679,
      "right_serve": 0.032306489220005244
    }
  },
  {
    "true_class": "left_serve",
    "frame": 55522,
    "predicted_class": "left_serve",
    "probabilities": {
      "left_backhand": 0.009424221342308638,
      "left_forehand": 0.31306322504919154,
      "left_serve": 0.6461350707859382,
      "right_backhand": 0.02127345766378822,
      "right_forehand": 0.002543414941857755,
      "right_serve": 0.007560610216915554
    }
  },
  {
    "true_class": "right_backhand",
    "frame": 55619,
    "predicted_class": "right_backhand",
    "probabilities": {
      "left_backhand": 0.012188800407482337,
      "left_forehand": 0.10885953656133222,
      "left_serve": 0.015386051360025148,
      "right_backhand": 0.8167965341699386,
      "right_forehand": 0.03279393826666246,
      "right_serve": 0.013975139234559179
    }
  },
  {
    "true_class": "left_forehand",
    "frame": 55711,
    "predicted_class": "left_forehand",
    "probabilities": {
      "left_backhand": 0.013456997248765288,
      "left_forehand": 0.9234083448863011,
      "left_serve": 0.04215561025184135,
      "right_backhand": 0.008503433578835292,
      "right_forehand": 0.005490911631176699,
      "right_serve": 0.006984702403080182
    }
  },
  {
    "true_class": "right_forehand",
    "frame": 55772,
    "predicted_class": "right_forehand",
    "probabilities": {
      "left_backhand": 0.06931250843286597,
      "left_forehand": 0.09059327598192034,
      "left_serve": 0.044457554881766,
      "right_backhand": 0.16367576372997503,
      "right_forehand": 0.565359365755253,
      "right_serve": 0.0666015312182197
    }
  },
  {
    "true_class": "left_backhand",
    "frame": 58225,
    "predicted_class": "left_backhand",
    "probabilities": {
      "left_backhand": 0.7838872494641733,
      "left_forehand": 0.10529751084217503,
      "left_serve": 0.03858993496461825,
      "right_backhand": 0.014920887847376467,
      "right_forehand": 0.01925272305116833,
      "right_serve": 0.038051693830488446
    }
  },
  {
    "true_class": "left_forehand",
    "frame": 58361,
    "predicted_class": "left_forehand",
    "probabilities": {
      "left_backhand": 0.008754176200820744,
      "left_forehand": 0.9437926433108439,
      "left_serve": 0.027728092457668968,
      "right_backhand": 0.004155870928860381,
      "right_forehand": 0.011444105838433445,
      "right_serve": 0.004125111263372457
    }
  },
  {
    "true_class": "right_forehand",
    "frame": 58415,
    "predicted_class": "right_forehand",
    "probabilities": {
      "left_backhand": 0.04206124625950142,
      "left_forehand": 0.11957921372848161,
      "left_serve": 0.07239347358003498,
      "right_backhand": 0.08037158302879102,
      "right_forehand": 0.6489116837095122,
      "right_serve": 0.036682799693678825
    }
  },
  {
    "true_class": "right_serve",
    "frame": 59186,
    "predicted_class": "right_serve",
    "probabilities": {
      "left_backhand": 0.1319278361948129,
      "left_forehand": 0.16333734109720352,
      "left_serve": 0.01979146093930081,
      "right_backhand": 0.27578760090507437,
      "right_forehand": 0.11050699914482846,
      "right_serve": 0.29864876171878
    }
  },
  {
    "true_class": "left_backhand",
    "frame": 59273,
    "predicted_class": "left_backhand",
    "probabilities": {
      "left_backhand": 0.5560819897055382,
      "left_forehand": 0.1914640816260746,
      "left_serve": 0.027523726050818653,
      "right_backhand": 0.11082353232093603,
      "right_forehand": 0.04048878212652121,
      "right_serve": 0.0736178881701113
    }
  },
  {
    "true_class": "right_backhand",
    "frame": 59327,
    "predicted_class": "right_backhand",
    "probabilities": {
      "left_backhand": 0.032911013788061896,
      "left_forehand": 0.13879195457742127,
      "left_serve": 0.029281301046499838,
      "right_backhand": 0.5420618842843606,
      "right_forehand": 0.23071759803480196,
      "right_serve": 0.026236248268854297
    }
  },
  {
    "true_class": "right_forehand",
    "frame": 59463,
    "predicted_class": "right_forehand",
    "probabilities": {
      "left_backhand": 0.025451995117855192,
      "left_forehand": 0.25498412037142837,
      "left_serve": 0.05636384505394343,
      "right_backhand": 0.12994308680976313,
      "right_forehand": 0.4160416264966966,
      "right_serve": 0.11721532615031333
    }
  },
  {
    "true_class": "left_backhand",
    "frame": 59541,
    "predicted_class": "left_forehand",
    "probabilities": {
      "left_backhand": 0.2545635132266412,
      "left_forehand": 0.26157723345692885,
      "left_serve": 0.16391181430632357,
      "right_backhand": 0.15364526899513054,
      "right_forehand": 0.12655983612020333,
      "right_serve": 0.03974233389477251
    }
  },
  {
    "true_class": "left_serve",
    "frame": 60987,
    "predicted_class": "left_backhand",
    "probabilities": {
      "left_backhand": 0.25320951109284745,
      "left_forehand": 0.20780516964800913,
      "left_serve": 0.14610369313242888,
      "right_backhand": 0.25051152907807855,
      "right_forehand": 0.10676344229172023,
      "right_serve": 0.03560665475691582
    }
  },
  {
    "true_class": "right_backhand",
    "frame": 61079,
    "predicted_class": "right_backhand",
    "probabilities": {
      "left_backhand": 0.024007198127767318,
      "left_forehand": 0.08909860289972546,
      "left_serve": 0.011124772076607024,
      "right_backhand": 0.7654161956319555,
      "right_forehand": 0.09407598649966505,
      "right_serve": 0.016277244764279667
    }
  },
  {
    "true_class": "left_forehand",
    "frame": 61154,
    "predicted_class": "left_forehand",
    "probabilities": {
      "left_backhand": 0.0011947676906936483,
      "left_forehand": 0.963334485486144,
      "left_serve": 0.00834626865771271,
      "right_backhand": 0.012141011520683507,
      "right_forehand": 0.013653783503508116,
      "right_serve": 0.0013296831412581524
    }
  },
  {
    "true_class": "left_serve",
    "frame": 62835,
    "predicted_class": "left_serve",
    "probabilities": {
      "left_backhand": 0.013470714424334417,
      "left_forehand": 0.44564313412800965,
      "left_serve": 0.513964825016137,
      "right_backhand": 0.0141267356802196,
      "right_forehand": 0.00473076540773304,
      "right_serve": 0.00806382534356624
    }
  },
  {
    "true_class": "right_backhand",
    "frame": 62914,
    "predicted_class": "right_backhand",
    "probabilities": {
      "left_backhand": 0.02020672043621122,
      "left_forehand": 0.12609843762731274,
      "left_serve": 0.026124482477271973,
      "right_backhand": 0.7524987667529431,
      "right_forehand": 0.04740330103731623,
      "right_serve": 0.027668291668944616
    }
  },
  {
    "true_class": "left_backhand",
    "frame": 62995,
    "predicted_class": "left_backhand",
    "probabilities": {
      "left_backhand": 0.46841363209743814,
      "left_forehand": 0.34519612962480944,
      "left_serve": 0.0402714810709551,
      "right_backhand": 0.09641427564950737,
      "right_forehand": 0.016851843657811578,
      "right_serve": 0.03285263789947822
    }
  },
  {
    "true_class": "right_backhand",
    "frame": 63079,
    "predicted_class": "right_backhand",
    "probabilities": {
      "left_backhand": 0.028807281445616725,
      "left_forehand": 0.28497979268041923,
      "left_serve": 0.05744182190274292,
      "right_backhand": 0.4867436184233749,
      "right_forehand": 0.118298688253204,
      "right_serve": 0.0237287972946423
    }
  },
  {
    "true_class": "left_forehand",
    "frame": 63168,
    "predicted_class": "left_forehand",
    "probabilities": {
      "left_backhand": 0.030031845795969694,
      "left_forehand": 0.8728064303490582,
      "left_serve": 0.07080216176526385,
      "right_backhand": 0.006392778970862497,
      "right_forehand": 0.009375287928675643,
      "right_serve": 0.010591495190170129
    }
  },
  {
    "true_class": "right_serve",
    "frame": 64143,
    "predicted_class": "right_serve",
    "probabilities": {
      "left_backhand": 0.17931411272269876,
      "left_forehand": 0.10843327732544396,
      "left_serve": 0.016453101364662402,
      "right_backhand": 0.2717097710222302,
      "right_forehand": 0.09685610320547598,
      "right_serve": 0.3272336343594887
    }
  },
  {
    "true_class": "left_backhand",
    "frame": 64235,
    "predicted_class": "left_backhand",
    "probabilities": {
      "left_backhand": 0.6978187114964749,
      "left_forehand": 0.13041398504454715,
      "left_serve": 0.02944156158440588,
      "right_backhand": 0.04926415186613786,
      "right_forehand": 0.062060676968475094,
      "right_serve": 0.031000913039959256
    }
  },
  {
    "true_class": "right_backhand",
    "frame": 64286,
    "predicted_class": "right_backhand",
    "probabilities": {
      "left_backhand": 0.05941584764964751,
      "left_forehand": 0.1263442975053815,
      "left_serve": 0.0449522900822608,
      "right_backhand": 0.6425983308883839,
      "right_forehand": 0.10145729643416455,
      "right_serve": 0.025231937440161747
    }
  },
  {
    "true_class": "left_forehand",
    "frame": 64391,
    "predicted_class": "left_forehand",
    "probabilities": {
      "left_backhand": 0.3999434608120711,
      "left_forehand": 0.49986020534365744,
      "left_serve": 0.038769582189836366,
      "right_backhand": 0.03418271532496866,
      "right_forehand": 0.01379805708390687,
      "right_serve": 0.013445979245559384
    }
  },
  {
    "true_class": "right_serve",
    "frame": 65423,
    "predicted_class": "right_serve",
    "probabilities": {
      "left_backhand": 0.248442557478428,
      "left_forehand": 0.06328858291199037,
      "left_serve": 0.04335763458834108,
      "right_backhand": 0.011281444049412634,
      "right_forehand": 0.018507826017391565,
      "right_serve": 0.6151219549544363
    }
  },
  {
    "true_class": "left_backhand",
    "frame": 65492,
    "predicted_class": "left_backhand",
    "probabilities": {
      "left_backhand": 0.7401018301502761,
      "left_forehand": 0.05740584152970263,
      "left_serve": 0.033728400694524305,
      "right_backhand": 0.030436225428064234,
      "right_forehand": 0.014505180823148289,
      "right_serve": 0.12382252137428452
    }
  },
  {
    "true_class": "right_forehand",
    "frame": 65575,
    "predicted_class": "right_forehand",
    "probabilities": {
      "left_backhand": 0.058391717431106764,
      "left_forehand": 0.2313159418998036,
      "left_serve": 0.005596330643725171,
      "right_backhand": 0.006101433475492212,
      "right_forehand": 0.6829787153287313,
      "right_serve": 0.01561586122114102
    }
  },
  {
    "true_class": "left_serve",
    "frame": 68367,
    "predicted_class": "left_serve",
    "probabilities": {
      "left_backhand": 0.016332519182185274,
      "left_forehand": 0.19182437459202173,
      "left_serve": 0.7470352549558752,
      "right_backhand": 0.029712338641850387,
      "right_forehand": 0.0048769245238286536,
      "right_serve": 0.010218588104238703
    }
  },
  {
    "true_class": "right_backhand",
    "frame": 68447,
    "predicted_class": "right_backhand",
    "probabilities": {
      "left_backhand": 0.020834318444978007,
      "left_forehand": 0.2908437985278171,
      "left_serve": 0.026949389983323205,
      "right_backhand": 0.6128599612815695,
      "right_forehand": 0.029755778214141024,
      "right_serve": 0.018756753548171006
    }
  },
  {
    "true_class": "left_forehand",
    "frame": 68560,
    "predicted_class": "left_forehand",
    "probabilities": {
      "left_backhand": 0.01359605216531198,
      "left_forehand": 0.9191277506734102,
      "left_serve": 0.0515329780596035,
      "right_backhand": 0.004972986649073469,
      "right_forehand": 0.00541875108135512,
      "right_serve": 0.005351481371245734
    }
  },
  {
    "true_class": "left_serve",
    "frame": 69290,
    "predicted_class": "left_serve",
    "probabilities": {
      "left_backhand": 0.017783855361242013,
      "left_forehand": 0.23352560363601566,
      "left_serve": 0.7159269847075797,
      "right_backhand": 0.02037672248718254,
      "right_forehand": 0.004041953769581153,
      "right_serve": 0.008344880038399014
    }
  },
  {
    "true_class": "right_backhand",
    "frame": 69380,
    "predicted_class": "right_backhand",
    "probabilities": {
      "left_backhand": 0.007265315953742049,
      "left_forehand": 0.08219361635526035,
      "left_serve": 0.012363286418263508,
      "right_backhand": 0.8603610666421878,
      "right_forehand": 0.029952036915551004,
      "right_serve": 0.007864677714995385
    }
  },
  {
    "true_class": "left_forehand",
    "frame": 69469,
    "predicted_class": "left_forehand",
    "probabilities": {
      "left_backhand": 0.019775638049595156,
      "left_forehand": 0.8478551617398139,
      "left_serve": 0.09086549615184537,
      "right_backhand": 0.02151425479836919,
      "right_forehand": 0.008445501279109832,
      "right_serve": 0.011543947981266603
    }
  },
  {
    "true_class": "right_forehand",
    "frame": 69520,
    "predicted_class": "right_forehand",
    "probabilities": {
      "left_backhand": 0.15304227625084915,
      "left_forehand": 0.12153674914259908,
      "left_serve": 0.12763235854337168,
      "right_backhand": 0.13582502133744534,
      "right_forehand": 0.34981460863419117,
      "right_serve": 0.11214898609154351
    }
  },
  {
    "true_class": "left_forehand",
    "frame": 69596,
    "predicted_class": "left_forehand",
    "probabilities": {
      "left_backhand": 0.0023436301948987085,
      "left_forehand": 0.9478085026859684,
      "left_serve": 0.01902080760496377,
      "right_backhand": 0.008783512147475869,
      "right_forehand": 0.015756184760892016,
      "right_serve": 0.006287362605801214
    }
  },
  {
    "true_class": "right_forehand",
    "frame": 69648,
    "predicted_class": "right_forehand",
    "probabilities": {
      "left_backhand": 0.07586019362312225,
      "left_forehand": 0.15710162566152602,
      "left_serve": 0.021191413709691718,
      "right_backhand": 0.13630482742036043,
      "right_forehand": 0.4856862395617437,
      "right_serve": 0.12385570002355581
    }
  },
  {
    "true_class": "left_forehand",
    "frame": 69932,
    "predicted_class": "left_forehand",
    "probabilities": {
      "left_backhand": 0.001953766988089544,
      "left_forehand": 0.9760578622180461,
      "left_serve": 6.296977549307114e-07,
      "right_backhand": 0.006658934468002372,
      "right_forehand": 0.015328806628106857,
      "right_serve": 2.7348512449651267e-26
    }
  },
  {
    "true_class": "right_serve",
    "frame": 71697,
    "predicted_class": "right_serve",
    "probabilities": {
      "left_backhand": 0.29914423725555883,
      "left_forehand": 0.07936990767103477,
      "left_serve": 0.05971505880231049,
      "right_backhand": 0.027952654603971016,
      "right_forehand": 0.04244503178437451,
      "right_serve": 0.4913731098827504
    }
  },
  {
    "true_class": "left_backhand",
    "frame": 71790,
    "predicted_class": "left_backhand",
    "probabilities": {
      "left_backhand": 0.6199540908423429,
      "left_forehand": 0.2093254762857933,
      "left_serve": 0.06819599141921699,
      "right_backhand": 0.018941131869925184,
      "right_forehand": 0.03435077468906599,
      "right_serve": 0.0492325348936557
    }
  },
  {
    "true_class": "left_serve",
    "frame": 73131,
    "predicted_class": "left_serve",
    "probabilities": {
      "left_backhand": 0.015881533237967132,
      "left_forehand": 0.21509454007014503,
      "left_serve": 0.7355516619554096,
      "right_backhand": 0.02131081976553439,
      "right_forehand": 0.0025594047583053546,
      "right_serve": 0.00960204021263846
    }
  }
]